flowx_sdk/__init__.py
flowx_sdk/cli.py
flowx_sdk/client.py
flowx_sdk/error_handler.py
flowx_sdk/liquidity.py
flowx_sdk/payments.py
flowx_sdk/rates.py
flowx_sdk/sign_device.py
flowx_sdk/transaction.py
flowx_sdk/utils.py
flowx_sdk/wallets.py
flowx_sdk/core/config.py
flowx_sdk-0.0.9.dist-info/METADATA
flowx_sdk-0.0.9.dist-info/WHEEL
flowx_sdk-0.0.9.dist-info/entry_points.txt
flowx_sdk-0.0.9.dist-info/RECORD
