Metadata-Version: 2.3
Name: flowx_sdk
Version: 0.0.9
Summary: the feature of blockchain
Project-URL: home, https://github.com/georgegoldman/FlowX.git
Author-email: George-Goldman <georgegoldmanjohn.o@gmail.com>
Classifier: License :: OSI Approved :: MIT License
Classifier: Operating System :: OS Independent
Classifier: Programming Language :: Python :: 3
Requires-Dist: aiohttp==3.11.7
Requires-Dist: asyncio==3.4.3
Requires-Dist: python-dotenv==1.0.1
Requires-Dist: requests==2.32.3
Requires-Dist: termcolor==2.5.0
